twweb/__init__.py
twweb/app.py
twweb/config.py
twweb/expect.py
twweb/fields.py
twweb/filters.py
twweb/forms.py
twweb/jinja.py
twweb/model.py
twweb/security.py
twweb/tw.py
twweb/utils.py
twweb/validators.py
twweb/version.py
twweb/static/icon-144.png
twweb/static/icon-192.png
twweb/static/icon-36.png
twweb/static/icon-48.png
twweb/static/icon-512.png
twweb/static/icon-72.png
twweb/static/icon-96.png
twweb/static/manifest.json
twweb/static/style.css
twweb/static/sw-register.js
twweb/static/sw.js
twweb/static/tww.js
twweb/templates/accordion.html
twweb/templates/cards.html
twweb/templates/edit.html
twweb/templates/error.html
twweb/templates/form-action.html
twweb/templates/index.html
twweb/templates/layout.html
twweb/templates/macros.html
twweb/templates/table.html
twweb/templates/task.html
twweb/views/__init__.py
twweb/views/pwa.py
twweb/views/task.py
twweb/views/view_utils.py
twweb-0.6.1.dist-info/DESCRIPTION.rst
twweb-0.6.1.dist-info/METADATA
twweb-0.6.1.dist-info/RECORD
twweb-0.6.1.dist-info/WHEEL
twweb-0.6.1.dist-info/metadata.json
twweb-0.6.1.dist-info/top_level.txt
