Metadata-Version: 2.0
Name: twweb
Version: 0.6.1
Summary: Taskwarrior Web View
Home-page: UNKNOWN
Author: Michał Góral
Author-email: dev@mgoral.org
License: GPLv3+
Platform: linux
Classifier: Development Status :: 3 - Alpha
Classifier: Environment :: Web Environment
Classifier: Framework :: Flask
Classifier: Intended Audience :: Developers
Classifier: Intended Audience :: System Administrators
Classifier: License :: OSI Approved :: GNU General Public License v3 or later (GPLv3+)
Classifier: Natural Language :: English
Classifier: Operating System :: POSIX
Classifier: Programming Language :: Python :: 3 :: Only
Classifier: Programming Language :: Python :: 3.5
Classifier: Programming Language :: Python :: 3.6
Classifier: Topic :: Internet :: WWW/HTTP :: WSGI :: Application
Classifier: Topic :: Utilities
Requires-Dist: Flask (==1.0.2)
Requires-Dist: flask-login (==0.4.1)
Requires-Dist: flask-sqlalchemy (==2.3.1)
Requires-Dist: flask-wtf (==0.14.2)
Requires-Dist: passlib (==1.7.1)
Requires-Dist: taskw (==1.2.0)
